{"text": "特斯拉的另一头，十万元新能源小车是个怎样的江湖？", "label": {"element": {"特斯拉": [[0, 2]]}}}
{"text": "零跑汽车，起个大早，赶个晚集？", "label": {"element": {"零跑汽车": [[0, 3]]}}}
{"text": "“守不住”和“打不进”：大众汽车驶入十字路口", "label": {"element": {"大众汽车": [[12, 15]]}}}
{"text": "Apple Car 之于苹果：属战略性机遇但并非救世主", "label": {"element": {"苹果": [[12, 13]]}}}
{"text": "华数传媒：高管发生人事变动", "label": {"element": {"华数传媒": [[0, 3]]}}}
{"text": "和元生物深度报告：细胞基因治疗CDMO高速成长，核心能力铸就一体化稀缺平台【东吴医药朱国广团队】", "label": {"element": {"东吴医药": [[38, 41]]}}}
{"text": "润阳科技股东减持135.28万股 套现3667.34万 2021年第三季度公司净利2119.43万", "label": {"element": {"润阳科技": [[0, 3]]}}}
{"text": "中国华融有望走出巨亏阴霾：2021年实现归母净利润3.7亿", "label": {"element": {"中国华融": [[0, 3]]}}}